<?xml version="1.0" encoding="UTF-8" standalone="yes"?><schools><school><gsId>1707</gsId><name>Skykomish Elementary School</name><type>public</type><gradeRange>PK-8</gradeRange><enrollment>28</enrollment><parentRating>3</parentRating><city>Skykomish</city><state>WA</state><districtId>238</districtId><district>Skykomish School District</district><districtNCESId>5307980</districtNCESId><address>105 6th St North, 
Skykomish, WA  98288</address><phone>(206) 677-2623</phone><fax></fax><website></website><ncesId>530798001320</ncesId><lat>47.7094</lat><lon>-121.3623</lon><overviewLink>http://www.greatschools.org/washington/skykomish/1707-Skykomish-Elementary-School/?s_cid=gsapi</overviewLink><ratingsLink>http://www.greatschools.org/school/rating.page?state=WA&amp;id=1707&amp;s_cid=gsapi</ratingsLink><reviewsLink>http://www.greatschools.org/school/parentReviews.page?state=WA&amp;id=1707&amp;s_cid=gsapi</reviewsLink><schoolStatsLink>http://www.greatschools.org/modperl/achievement/WA/1707</schoolStatsLink></school><school><gsId>1708</gsId><name>Skykomish High School</name><type>public</type><gradeRange>9-12</gradeRange><enrollment>14</enrollment><parentRating>3</parentRating><city>Skykomish</city><state>WA</state><districtId>238</districtId><district>Skykomish School District</district><districtNCESId>5307980</districtNCESId><address>105 6th St North, 
Skykomish, WA  98288</address><phone>(206) 677-2623</phone><fax></fax><website></website><ncesId>530798001321</ncesId><lat>47.7094</lat><lon>-121.3623</lon><overviewLink>http://www.greatschools.org/washington/skykomish/1708-Skykomish-High-School/?s_cid=gsapi</overviewLink><ratingsLink>http://www.greatschools.org/school/rating.page?state=WA&amp;id=1708&amp;s_cid=gsapi</ratingsLink><reviewsLink>http://www.greatschools.org/school/parentReviews.page?state=WA&amp;id=1708&amp;s_cid=gsapi</reviewsLink><schoolStatsLink>http://www.greatschools.org/modperl/achievement/WA/1708</schoolStatsLink></school></schools>